{"t": "Chapter 6D. Long-Term Care Study.", "p": "/dc/council/code/titles/7/chapters/6D/", "et": "container", "dj": "/dc/council/code/index.json", "sc": "Chapter 6D of Title 7", "c": [{"t": "\u00a7 7\u2013681. Definitions. [Not Funded]", "p": "/dc/council/code/sections/7-681.html", "et": "section", "sc": "\u00a7 7-681"}, {"t": "\u00a7 7\u2013682. Study of long-term care facilities and long-term care services. [Not Funded]", "p": "/dc/council/code/sections/7-682.html", "et": "section", "sc": "\u00a7 7-682"}]}