{"t": "Chapter 3. Commissioned Officers.", "p": "/dc/council/code/titles/49/chapters/3/", "et": "container", "dj": "/dc/council/code/index.json", "sc": "Chapter 3 of Title 49", "c": [{"t": "\u00a7 49\u2013301. Commanding General.", "p": "/dc/council/code/sections/49-301.html", "et": "section", "sc": "\u00a7 49-301", "c": [{"t": "(a)", "p": "/dc/council/code/sections/49-301.html#(a)", "et": "para", "sc": "\u00a7 49-301(a)", "x": "There shall be appointed and commissioned by the President of the United St"}, {"t": "(b)", "p": "/dc/council/code/sections/49-301.html#(b)", "et": "para", "sc": "\u00a7 49-301(b)", "x": "Except as provided in subsection (c) of this section, any person serving as"}, {"t": "(c)", "p": "/dc/council/code/sections/49-301.html#(c)", "et": "para", "sc": "\u00a7 49-301(c)", "x": "Any officer of the armed forces of the United States who, while serving on "}]}, {"t": "\u00a7 49\u2013302. Staff officers; noncommissioned staff.", "p": "/dc/council/code/sections/49-302.html", "et": "section", "sc": "\u00a7 49-302"}, {"t": "\u00a7 49\u2013303. Qualifications of staff officers; tenure; vacancies.", "p": "/dc/council/code/sections/49-303.html", "et": "section", "sc": "\u00a7 49-303"}, {"t": "\u00a7 49\u2013304. Adjutant General.", "p": "/dc/council/code/sections/49-304.html", "et": "section", "sc": "\u00a7 49-304"}, {"t": "\u00a7 49\u2013305. Officers.", "p": "/dc/council/code/sections/49-305.html", "et": "section", "sc": "\u00a7 49-305"}, {"t": "\u00a7 49\u2013306. Officers of staff departments.", "p": "/dc/council/code/sections/49-306.html", "et": "section", "sc": "\u00a7 49-306"}, {"t": "\u00a7 49\u2013307. Filling vacancies above the grade of 2nd lieutenant.", "p": "/dc/council/code/sections/49-307.html", "et": "section", "sc": "\u00a7 49-307"}, {"t": "\u00a7 49\u2013308. Appointments to grade of 2nd lieutenant.", "p": "/dc/council/code/sections/49-308.html", "et": "section", "sc": "\u00a7 49-308"}, {"t": "\u00a7 49\u2013309. Examinations for promotion; failure to appear; retirement for disability.", "p": "/dc/council/code/sections/49-309.html", "et": "section", "sc": "\u00a7 49-309"}, {"t": "\u00a7 49\u2013310. Examinations for 2nd lieutenants.", "p": "/dc/council/code/sections/49-310.html", "et": "section", "sc": "\u00a7 49-310"}, {"t": "\u00a7 49\u2013311. Special examination of officer\u2019s capability.", "p": "/dc/council/code/sections/49-311.html", "et": "section", "sc": "\u00a7 49-311", "c": [{"t": "(a)", "p": "/dc/council/code/sections/49-311.html#(a)", "et": "para", "sc": "\u00a7 49-311(a)", "x": "Whenever, in the opinion of the Commanding General of the militia of the Di"}, {"t": "(b)", "p": "/dc/council/code/sections/49-311.html#(b)", "et": "para", "sc": "\u00a7 49-311(b)", "x": "If any officer shall fail to appear before a board of examination so appoin"}]}, {"t": "\u00a7 49\u2013312. Retirement of commissioned officer.", "p": "/dc/council/code/sections/49-312.html", "et": "section", "sc": "\u00a7 49-312"}, {"t": "\u00a7 49\u2013313. Discharge of commissioned officer.", "p": "/dc/council/code/sections/49-313.html", "et": "section", "sc": "\u00a7 49-313", "c": [{"t": "(a)", "p": "/dc/council/code/sections/49-313.html#(a)", "et": "para", "sc": "\u00a7 49-313(a)", "c": [{"t": "(1)", "p": "/dc/council/code/sections/49-313.html#(a)(1)", "et": "para", "sc": "\u00a7 49-313(a)(1)", "x": "Upon tender of resignation;"}, {"t": "(2)", "p": "/dc/council/code/sections/49-313.html#(a)(2)", "et": "para", "sc": "\u00a7 49-313(a)(2)", "x": "Upon disbandment of the organization to which he belongs; or"}, {"t": "(3)", "p": "/dc/council/code/sections/49-313.html#(a)(3)", "et": "para", "sc": "\u00a7 49-313(a)(3)", "x": "Upon report of a board of examination, or for failure to appear before such"}], "x": "A commissioned officer may be honorably discharged:"}, {"t": "(b)", "p": "/dc/council/code/sections/49-313.html#(b)", "et": "para", "sc": "\u00a7 49-313(b)", "x": "He may be dismissed upon the sentence of a court-martial, or conviction in "}]}]}