{"t": "D.C. Law 21-201. Feminine Hygiene and Diaper Sales Tax Exemption Amendment Act of 2016.", "p": "/dc/council/laws/21-201.html", "et": "document", "sc": "D.C. Law 21-201", "c": [{"t": "\u00a7 2.", "p": "/dc/council/laws/21-201.html#\u00a72", "et": "section", "sc": "\u00a7 2", "c": [{"t": "(a)", "p": "/dc/council/laws/21-201.html#\u00a72(a)", "et": "para", "sc": "\u00a7 2(a)", "x": "Paragraph (36) is amended by striking the word \"and\"."}, {"t": "(b)", "p": "/dc/council/laws/21-201.html#\u00a72(b)", "et": "para", "sc": "\u00a7 2(b)", "x": "New paragraphs (38) and (39) are added to read as follows:"}], "x": "Section 47-2005 of the District of Columbia Official Code is amended as fol"}, {"t": "\u00a7 3. Applicability. [Repealed]", "p": "/dc/council/laws/21-201.html#\u00a73", "et": "section", "sc": "\u00a7 3"}, {"t": "\u00a7 4. Fiscal impact statement.", "p": "/dc/council/laws/21-201.html#\u00a74", "et": "section", "sc": "\u00a7 4"}, {"t": "\u00a7 5. Effective date.", "p": "/dc/council/laws/21-201.html#\u00a75", "et": "section", "sc": "\u00a7 5"}]}