{"t": "D.C. Law 5-146. District of Columbia Right to Overnight Shelter Act of 1984.", "p": "/dc/council/laws/5-146.html", "et": "document", "sc": "D.C. Law 5-146", "c": [{"t": "\u00a7 2.", "p": "/dc/council/laws/5-146.html#\u00a72", "et": "section", "sc": "\u00a7 2"}, {"t": "\u00a7 3a.", "p": "/dc/council/laws/5-146.html#\u00a73a", "et": "section", "sc": "\u00a7 3a"}, {"t": "\u00a7 4.", "p": "/dc/council/laws/5-146.html#\u00a74", "et": "section", "sc": "\u00a7 4"}, {"t": "\u00a7 5.", "p": "/dc/council/laws/5-146.html#\u00a75", "et": "section", "sc": "\u00a7 5"}, {"t": "\u00a7 6.", "p": "/dc/council/laws/5-146.html#\u00a76", "et": "section", "sc": "\u00a7 6"}, {"t": "\u00a7 6a.", "p": "/dc/council/laws/5-146.html#\u00a76a", "et": "section", "sc": "\u00a7 6a"}, {"t": "\u00a7 7.", "p": "/dc/council/laws/5-146.html#\u00a77", "et": "section", "sc": "\u00a7 7"}, {"t": "\u00a7 8.", "p": "/dc/council/laws/5-146.html#\u00a78", "et": "section", "sc": "\u00a7 8"}, {"t": "\u00a7 8a.", "p": "/dc/council/laws/5-146.html#\u00a78a", "et": "section", "sc": "\u00a7 8a"}, {"t": "\u00a7 8b.", "p": "/dc/council/laws/5-146.html#\u00a78b", "et": "section", "sc": "\u00a7 8b"}, {"t": "\u00a7 8c.", "p": "/dc/council/laws/5-146.html#\u00a78c", "et": "section", "sc": "\u00a7 8c"}, {"t": "\u00a7 8d.", "p": "/dc/council/laws/5-146.html#\u00a78d", "et": "section", "sc": "\u00a7 8d"}, {"t": "\u00a7 8e.", "p": "/dc/council/laws/5-146.html#\u00a78e", "et": "section", "sc": "\u00a7 8e"}, {"t": "\u00a7 8f.", "p": "/dc/council/laws/5-146.html#\u00a78f", "et": "section", "sc": "\u00a7 8f"}, {"t": "\u00a7 9.", "p": "/dc/council/laws/5-146.html#\u00a79", "et": "section", "sc": "\u00a7 9"}]}