{"t": "D.C. Law 6-97.", "p": "/dc/council/laws/6-97.html", "et": "document", "sc": "D.C. Law 6-97", "c": [{"t": "\u00a7 2.", "p": "/dc/council/laws/6-97.html#\u00a72", "et": "section", "sc": "\u00a7 2", "c": [{"t": "\u00a7 2.", "p": "/dc/council/laws/6-97.html#\u00a72", "et": "section", "sc": "\u00a7 2", "c": [{"t": "\u00a7 2.", "p": "/dc/council/laws/6-97.html#\u00a72", "et": "section", "sc": "\u00a7 2"}]}]}, {"t": "\u00a7 3.", "p": "/dc/council/laws/6-97.html#\u00a73", "et": "section", "sc": "\u00a7 3", "c": [{"t": "\u00a7 3.", "p": "/dc/council/laws/6-97.html#\u00a73", "et": "section", "sc": "\u00a7 3", "c": [{"t": "\u00a7 3.", "p": "/dc/council/laws/6-97.html#\u00a73", "et": "section", "sc": "\u00a7 3"}]}]}, {"t": "\u00a7 4.", "p": "/dc/council/laws/6-97.html#\u00a74", "et": "section", "sc": "\u00a7 4", "c": [{"t": "\u00a7 4.", "p": "/dc/council/laws/6-97.html#\u00a74", "et": "section", "sc": "\u00a7 4", "c": [{"t": "\u00a7 4.", "p": "/dc/council/laws/6-97.html#\u00a74", "et": "section", "sc": "\u00a7 4"}]}]}, {"t": "\u00a7 5.", "p": "/dc/council/laws/6-97.html#\u00a75", "et": "section", "sc": "\u00a7 5", "c": [{"t": "\u00a7 5.", "p": "/dc/council/laws/6-97.html#\u00a75", "et": "section", "sc": "\u00a7 5", "c": [{"t": "\u00a7 5.", "p": "/dc/council/laws/6-97.html#\u00a75", "et": "section", "sc": "\u00a7 5"}]}]}, {"t": "\u00a7 6.", "p": "/dc/council/laws/6-97.html#\u00a76", "et": "section", "sc": "\u00a7 6", "c": [{"t": "\u00a7 6.", "p": "/dc/council/laws/6-97.html#\u00a76", "et": "section", "sc": "\u00a7 6", "c": [{"t": "\u00a7 6.", "p": "/dc/council/laws/6-97.html#\u00a76", "et": "section", "sc": "\u00a7 6"}]}]}, {"t": "\u00a7 7.", "p": "/dc/council/laws/6-97.html#\u00a77", "et": "section", "sc": "\u00a7 7", "c": [{"t": "\u00a7 7.", "p": "/dc/council/laws/6-97.html#\u00a77", "et": "section", "sc": "\u00a7 7", "c": [{"t": "\u00a7 7.", "p": "/dc/council/laws/6-97.html#\u00a77", "et": "section", "sc": "\u00a7 7"}]}]}, {"t": "\u00a7 8.", "p": "/dc/council/laws/6-97.html#\u00a78", "et": "section", "sc": "\u00a7 8", "c": [{"t": "\u00a7 8.", "p": "/dc/council/laws/6-97.html#\u00a78", "et": "section", "sc": "\u00a7 8", "c": [{"t": "\u00a7 8.", "p": "/dc/council/laws/6-97.html#\u00a78", "et": "section", "sc": "\u00a7 8"}]}]}, {"t": "\u00a7 8a.", "p": "/dc/council/laws/6-97.html#\u00a78a", "et": "section", "sc": "\u00a7 8a", "c": [{"t": "\u00a7 8a.", "p": "/dc/council/laws/6-97.html#\u00a78a", "et": "section", "sc": "\u00a7 8a", "c": [{"t": "\u00a7 8a.", "p": "/dc/council/laws/6-97.html#\u00a78a", "et": "section", "sc": "\u00a7 8a"}]}]}, {"t": "\u00a7 8b.", "p": "/dc/council/laws/6-97.html#\u00a78b", "et": "section", "sc": "\u00a7 8b", "c": [{"t": "\u00a7 8b.", "p": "/dc/council/laws/6-97.html#\u00a78b", "et": "section", "sc": "\u00a7 8b", "c": [{"t": "\u00a7 8b.", "p": "/dc/council/laws/6-97.html#\u00a78b", "et": "section", "sc": "\u00a7 8b"}]}]}, {"t": "\u00a7 9.", "p": "/dc/council/laws/6-97.html#\u00a79", "et": "section", "sc": "\u00a7 9", "c": [{"t": "\u00a7 9.", "p": "/dc/council/laws/6-97.html#\u00a79", "et": "section", "sc": "\u00a7 9", "c": [{"t": "\u00a7 9.", "p": "/dc/council/laws/6-97.html#\u00a79", "et": "section", "sc": "\u00a7 9"}]}]}, {"t": "\u00a7 10.", "p": "/dc/council/laws/6-97.html#\u00a710", "et": "section", "sc": "\u00a7 10", "c": [{"t": "\u00a7 10.", "p": "/dc/council/laws/6-97.html#\u00a710", "et": "section", "sc": "\u00a7 10", "c": [{"t": "\u00a7 10.", "p": "/dc/council/laws/6-97.html#\u00a710", "et": "section", "sc": "\u00a7 10"}]}]}, {"t": "\u00a7 10a.", "p": "/dc/council/laws/6-97.html#\u00a710a", "et": "section", "sc": "\u00a7 10a", "c": [{"t": "\u00a7 10a.", "p": "/dc/council/laws/6-97.html#\u00a710a", "et": "section", "sc": "\u00a7 10a", "c": [{"t": "\u00a7 10a.", "p": "/dc/council/laws/6-97.html#\u00a710a", "et": "section", "sc": "\u00a7 10a"}]}]}, {"t": "\u00a7 10b.", "p": "/dc/council/laws/6-97.html#\u00a710b", "et": "section", "sc": "\u00a7 10b", "c": [{"t": "\u00a7 10b.", "p": "/dc/council/laws/6-97.html#\u00a710b", "et": "section", "sc": "\u00a7 10b", "c": [{"t": "\u00a7 10b.", "p": "/dc/council/laws/6-97.html#\u00a710b", "et": "section", "sc": "\u00a7 10b"}]}]}, {"t": "\u00a7 11.", "p": "/dc/council/laws/6-97.html#\u00a711", "et": "section", "sc": "\u00a7 11", "c": [{"t": "\u00a7 11.", "p": "/dc/council/laws/6-97.html#\u00a711", "et": "section", "sc": "\u00a7 11", "c": [{"t": "\u00a7 11.", "p": "/dc/council/laws/6-97.html#\u00a711", "et": "section", "sc": "\u00a7 11"}]}]}, {"t": "\u00a7 12.", "p": "/dc/council/laws/6-97.html#\u00a712", "et": "section", "sc": "\u00a7 12", "c": [{"t": "\u00a7 12.", "p": "/dc/council/laws/6-97.html#\u00a712", "et": "section", "sc": "\u00a7 12", "c": [{"t": "\u00a7 12.", "p": "/dc/council/laws/6-97.html#\u00a712", "et": "section", "sc": "\u00a7 12"}]}]}, {"t": "\u00a7 13.", "p": "/dc/council/laws/6-97.html#\u00a713", "et": "section", "sc": "\u00a7 13", "c": [{"t": "\u00a7 13.", "p": "/dc/council/laws/6-97.html#\u00a713", "et": "section", "sc": "\u00a7 13", "c": [{"t": "\u00a7 13.", "p": "/dc/council/laws/6-97.html#\u00a713", "et": "section", "sc": "\u00a7 13"}]}]}, {"t": "\u00a7 14.", "p": "/dc/council/laws/6-97.html#\u00a714", "et": "section", "sc": "\u00a7 14", "c": [{"t": "\u00a7 14.", "p": "/dc/council/laws/6-97.html#\u00a714", "et": "section", "sc": "\u00a7 14", "c": [{"t": "\u00a7 14.", "p": "/dc/council/laws/6-97.html#\u00a714", "et": "section", "sc": "\u00a7 14"}]}]}, {"t": "\u00a7 15.", "p": "/dc/council/laws/6-97.html#\u00a715", "et": "section", "sc": "\u00a7 15", "c": [{"t": "\u00a7 15.", "p": "/dc/council/laws/6-97.html#\u00a715", "et": "section", "sc": "\u00a7 15", "c": [{"t": "\u00a7 15.", "p": "/dc/council/laws/6-97.html#\u00a715", "et": "section", "sc": "\u00a7 15"}]}]}, {"t": "\u00a7 16.", "p": "/dc/council/laws/6-97.html#\u00a716", "et": "section", "sc": "\u00a7 16", "c": [{"t": "\u00a7 16.", "p": "/dc/council/laws/6-97.html#\u00a716", "et": "section", "sc": "\u00a7 16", "c": [{"t": "\u00a7 16.", "p": "/dc/council/laws/6-97.html#\u00a716", "et": "section", "sc": "\u00a7 16"}]}]}, {"t": "\u00a7 17.", "p": "/dc/council/laws/6-97.html#\u00a717", "et": "section", "sc": "\u00a7 17", "c": [{"t": "\u00a7 17.", "p": "/dc/council/laws/6-97.html#\u00a717", "et": "section", "sc": "\u00a7 17", "c": [{"t": "\u00a7 17.", "p": "/dc/council/laws/6-97.html#\u00a717", "et": "section", "sc": "\u00a7 17"}]}]}, {"t": "\u00a7 18.", "p": "/dc/council/laws/6-97.html#\u00a718", "et": "section", "sc": "\u00a7 18", "c": [{"t": "\u00a7 18.", "p": "/dc/council/laws/6-97.html#\u00a718", "et": "section", "sc": "\u00a7 18", "c": [{"t": "\u00a7 18.", "p": "/dc/council/laws/6-97.html#\u00a718", "et": "section", "sc": "\u00a7 18"}]}]}, {"t": "\u00a7 19.", "p": "/dc/council/laws/6-97.html#\u00a719", "et": "section", "sc": "\u00a7 19", "c": [{"t": "\u00a7 19.", "p": "/dc/council/laws/6-97.html#\u00a719", "et": "section", "sc": "\u00a7 19", "c": [{"t": "\u00a7 19.", "p": "/dc/council/laws/6-97.html#\u00a719", "et": "section", "sc": "\u00a7 19"}]}]}, {"t": "\u00a7 20.", "p": "/dc/council/laws/6-97.html#\u00a720", "et": "section", "sc": "\u00a7 20", "c": [{"t": "\u00a7 20.", "p": "/dc/council/laws/6-97.html#\u00a720", "et": "section", "sc": "\u00a7 20", "c": [{"t": "\u00a7 20.", "p": "/dc/council/laws/6-97.html#\u00a720", "et": "section", "sc": "\u00a7 20"}]}]}, {"t": "\u00a7 20a.", "p": "/dc/council/laws/6-97.html#\u00a720a", "et": "section", "sc": "\u00a7 20a", "c": [{"t": "\u00a7 20a.", "p": "/dc/council/laws/6-97.html#\u00a720a", "et": "section", "sc": "\u00a7 20a", "c": [{"t": "\u00a7 20a.", "p": "/dc/council/laws/6-97.html#\u00a720a", "et": "section", "sc": "\u00a7 20a"}]}]}, {"t": "\u00a7 20b.", "p": "/dc/council/laws/6-97.html#\u00a720b", "et": "section", "sc": "\u00a7 20b", "c": [{"t": "\u00a7 20b.", "p": "/dc/council/laws/6-97.html#\u00a720b", "et": "section", "sc": "\u00a7 20b", "c": [{"t": "\u00a7 20b.", "p": "/dc/council/laws/6-97.html#\u00a720b", "et": "section", "sc": "\u00a7 20b"}]}]}, {"t": "\u00a7 20c.", "p": "/dc/council/laws/6-97.html#\u00a720c", "et": "section", "sc": "\u00a7 20c", "c": [{"t": "\u00a7 20c.", "p": "/dc/council/laws/6-97.html#\u00a720c", "et": "section", "sc": "\u00a7 20c", "c": [{"t": "\u00a7 20c.", "p": "/dc/council/laws/6-97.html#\u00a720c", "et": "section", "sc": "\u00a7 20c"}]}]}, {"t": "\u00a7 20d.", "p": "/dc/council/laws/6-97.html#\u00a720d", "et": "section", "sc": "\u00a7 20d", "c": [{"t": "\u00a7 20d.", "p": "/dc/council/laws/6-97.html#\u00a720d", "et": "section", "sc": "\u00a7 20d", "c": [{"t": "\u00a7 20d.", "p": "/dc/council/laws/6-97.html#\u00a720d", "et": "section", "sc": "\u00a7 20d"}]}]}, {"t": "\u00a7 20e.", "p": "/dc/council/laws/6-97.html#\u00a720e", "et": "section", "sc": "\u00a7 20e", "c": [{"t": "\u00a7 20e.", "p": "/dc/council/laws/6-97.html#\u00a720e", "et": "section", "sc": "\u00a7 20e", "c": [{"t": "\u00a7 20e.", "p": "/dc/council/laws/6-97.html#\u00a720e", "et": "section", "sc": "\u00a7 20e"}]}]}, {"t": "\u00a7 20f.", "p": "/dc/council/laws/6-97.html#\u00a720f", "et": "section", "sc": "\u00a7 20f", "c": [{"t": "\u00a7 20f.", "p": "/dc/council/laws/6-97.html#\u00a720f", "et": "section", "sc": "\u00a7 20f", "c": [{"t": "\u00a7 20f.", "p": "/dc/council/laws/6-97.html#\u00a720f", "et": "section", "sc": "\u00a7 20f"}]}]}, {"t": "\u00a7 20f-1.", "p": "/dc/council/laws/6-97.html#\u00a720f-1", "et": "section", "sc": "\u00a7 20f-1", "c": [{"t": "\u00a7 20f-1.", "p": "/dc/council/laws/6-97.html#\u00a720f-1", "et": "section", "sc": "\u00a7 20f-1", "c": [{"t": "\u00a7 20f-1.", "p": "/dc/council/laws/6-97.html#\u00a720f-1", "et": "section", "sc": "\u00a7 20f-1"}]}]}, {"t": "\u00a7 20f-2.", "p": "/dc/council/laws/6-97.html#\u00a720f-2", "et": "section", "sc": "\u00a7 20f-2", "c": [{"t": "\u00a7 20f-2.", "p": "/dc/council/laws/6-97.html#\u00a720f-2", "et": "section", "sc": "\u00a7 20f-2", "c": [{"t": "\u00a7 20f-2.", "p": "/dc/council/laws/6-97.html#\u00a720f-2", "et": "section", "sc": "\u00a7 20f-2"}]}]}, {"t": "\u00a7 20g.", "p": "/dc/council/laws/6-97.html#\u00a720g", "et": "section", "sc": "\u00a7 20g", "c": [{"t": "\u00a7 20g.", "p": "/dc/council/laws/6-97.html#\u00a720g", "et": "section", "sc": "\u00a7 20g", "c": [{"t": "\u00a7 20g.", "p": "/dc/council/laws/6-97.html#\u00a720g", "et": "section", "sc": "\u00a7 20g"}]}]}, {"t": "\u00a7 20h.", "p": "/dc/council/laws/6-97.html#\u00a720h", "et": "section", "sc": "\u00a7 20h", "c": [{"t": "\u00a7 20h.", "p": "/dc/council/laws/6-97.html#\u00a720h", "et": "section", "sc": "\u00a7 20h", "c": [{"t": "\u00a7 20h.", "p": "/dc/council/laws/6-97.html#\u00a720h", "et": "section", "sc": "\u00a7 20h"}]}]}, {"t": "\u00a7 20i.", "p": "/dc/council/laws/6-97.html#\u00a720i", "et": "section", "sc": "\u00a7 20i", "c": [{"t": "\u00a7 20i.", "p": "/dc/council/laws/6-97.html#\u00a720i", "et": "section", "sc": "\u00a7 20i", "c": [{"t": "\u00a7 20i.", "p": "/dc/council/laws/6-97.html#\u00a720i", "et": "section", "sc": "\u00a7 20i"}]}]}, {"t": "\u00a7 20j.", "p": "/dc/council/laws/6-97.html#\u00a720j", "et": "section", "sc": "\u00a7 20j", "c": [{"t": "\u00a7 20j.", "p": "/dc/council/laws/6-97.html#\u00a720j", "et": "section", "sc": "\u00a7 20j", "c": [{"t": "\u00a7 20j.", "p": "/dc/council/laws/6-97.html#\u00a720j", "et": "section", "sc": "\u00a7 20j"}]}]}, {"t": "\u00a7 20j-1.", "p": "/dc/council/laws/6-97.html#\u00a720j-1", "et": "section", "sc": "\u00a7 20j-1", "c": [{"t": "\u00a7 20j-1.", "p": "/dc/council/laws/6-97.html#\u00a720j-1", "et": "section", "sc": "\u00a7 20j-1", "c": [{"t": "\u00a7 20j-1.", "p": "/dc/council/laws/6-97.html#\u00a720j-1", "et": "section", "sc": "\u00a7 20j-1"}]}]}, {"t": "\u00a7 20j-2.", "p": "/dc/council/laws/6-97.html#\u00a720j-2", "et": "section", "sc": "\u00a7 20j-2", "c": [{"t": "\u00a7 20j-2.", "p": "/dc/council/laws/6-97.html#\u00a720j-2", "et": "section", "sc": "\u00a7 20j-2", "c": [{"t": "\u00a7 20j-2.", "p": "/dc/council/laws/6-97.html#\u00a720j-2", "et": "section", "sc": "\u00a7 20j-2"}]}]}, {"t": "\u00a7 20j-3.", "p": "/dc/council/laws/6-97.html#\u00a720j-3", "et": "section", "sc": "\u00a7 20j-3", "c": [{"t": "\u00a7 20j-3.", "p": "/dc/council/laws/6-97.html#\u00a720j-3", "et": "section", "sc": "\u00a7 20j-3", "c": [{"t": "\u00a7 20j-3.", "p": "/dc/council/laws/6-97.html#\u00a720j-3", "et": "section", "sc": "\u00a7 20j-3"}]}]}, {"t": "\u00a7 20j-4.", "p": "/dc/council/laws/6-97.html#\u00a720j-4", "et": "section", "sc": "\u00a7 20j-4", "c": [{"t": "\u00a7 20j-4.", "p": "/dc/council/laws/6-97.html#\u00a720j-4", "et": "section", "sc": "\u00a7 20j-4", "c": [{"t": "\u00a7 20j-4.", "p": "/dc/council/laws/6-97.html#\u00a720j-4", "et": "section", "sc": "\u00a7 20j-4"}]}]}, {"t": "\u00a7 20j-5.", "p": "/dc/council/laws/6-97.html#\u00a720j-5", "et": "section", "sc": "\u00a7 20j-5", "c": [{"t": "\u00a7 20j-5.", "p": "/dc/council/laws/6-97.html#\u00a720j-5", "et": "section", "sc": "\u00a7 20j-5", "c": [{"t": "\u00a7 20j-5.", "p": "/dc/council/laws/6-97.html#\u00a720j-5", "et": "section", "sc": "\u00a7 20j-5"}]}]}, {"t": "\u00a7 20j-6.", "p": "/dc/council/laws/6-97.html#\u00a720j-6", "et": "section", "sc": "\u00a7 20j-6", "c": [{"t": "\u00a7 20j-6.", "p": "/dc/council/laws/6-97.html#\u00a720j-6", "et": "section", "sc": "\u00a7 20j-6", "c": [{"t": "\u00a7 20j-6.", "p": "/dc/council/laws/6-97.html#\u00a720j-6", "et": "section", "sc": "\u00a7 20j-6"}]}]}, {"t": "\u00a7 20j-7.", "p": "/dc/council/laws/6-97.html#\u00a720j-7", "et": "section", "sc": "\u00a7 20j-7", "c": [{"t": "\u00a7 20j-7.", "p": "/dc/council/laws/6-97.html#\u00a720j-7", "et": "section", "sc": "\u00a7 20j-7", "c": [{"t": "\u00a7 20j-7.", "p": "/dc/council/laws/6-97.html#\u00a720j-7", "et": "section", "sc": "\u00a7 20j-7"}]}]}, {"t": "\u00a7 20k.", "p": "/dc/council/laws/6-97.html#\u00a720k", "et": "section", "sc": "\u00a7 20k", "c": [{"t": "\u00a7 20k.", "p": "/dc/council/laws/6-97.html#\u00a720k", "et": "section", "sc": "\u00a7 20k", "c": [{"t": "\u00a7 20k.", "p": "/dc/council/laws/6-97.html#\u00a720k", "et": "section", "sc": "\u00a7 20k"}]}]}, {"t": "\u00a7 20l.", "p": "/dc/council/laws/6-97.html#\u00a720l", "et": "section", "sc": "\u00a7 20l", "c": [{"t": "\u00a7 20l.", "p": "/dc/council/laws/6-97.html#\u00a720l", "et": "section", "sc": "\u00a7 20l", "c": [{"t": "\u00a7 20l.", "p": "/dc/council/laws/6-97.html#\u00a720l", "et": "section", "sc": "\u00a7 20l"}]}]}, {"t": "\u00a7 20m.", "p": "/dc/council/laws/6-97.html#\u00a720m", "et": "section", "sc": "\u00a7 20m", "c": [{"t": "\u00a7 20m.", "p": "/dc/council/laws/6-97.html#\u00a720m", "et": "section", "sc": "\u00a7 20m", "c": [{"t": "\u00a7 20m.", "p": "/dc/council/laws/6-97.html#\u00a720m", "et": "section", "sc": "\u00a7 20m"}]}]}, {"t": "\u00a7 20n.", "p": "/dc/council/laws/6-97.html#\u00a720n", "et": "section", "sc": "\u00a7 20n", "c": [{"t": "\u00a7 20n.", "p": "/dc/council/laws/6-97.html#\u00a720n", "et": "section", "sc": "\u00a7 20n", "c": [{"t": "\u00a7 20n.", "p": "/dc/council/laws/6-97.html#\u00a720n", "et": "section", "sc": "\u00a7 20n"}]}]}, {"t": "\u00a7 20o.", "p": "/dc/council/laws/6-97.html#\u00a720o", "et": "section", "sc": "\u00a7 20o", "c": [{"t": "\u00a7 20o.", "p": "/dc/council/laws/6-97.html#\u00a720o", "et": "section", "sc": "\u00a7 20o", "c": [{"t": "\u00a7 20o.", "p": "/dc/council/laws/6-97.html#\u00a720o", "et": "section", "sc": "\u00a7 20o"}]}]}]}