{"t": "Chapter 29A. Closed Malpractice Claims.", "p": "/dc/council/code/titles/31/chapters/29A/", "et": "container", "dj": "/dc/council/code/index.json", "sc": "Chapter 29A of Title 31", "c": [{"t": "\u00a7 31\u20132991. Closed claim analysis.", "p": "/dc/council/code/sections/31-2991.html", "et": "section", "sc": "\u00a7 31-2991", "c": [{"t": "(a)", "p": "/dc/council/code/sections/31-2991.html#(a)", "et": "para", "sc": "\u00a7 31-2991(a)", "x": "Within 180 days of march 14, 2007, the Mayor shall submit legislation to th"}, {"t": "(b)", "p": "/dc/council/code/sections/31-2991.html#(b)", "et": "para", "sc": "\u00a7 31-2991(b)", "c": [{"t": "(A)", "p": "/dc/council/code/sections/31-2991.html#(b)(A)", "et": "para", "sc": "\u00a7 31-2991(b)(A)", "x": "Contain provisions to identify trends and develop recommendations for preve"}, {"t": "(B)", "p": "/dc/council/code/sections/31-2991.html#(b)(B)", "et": "para", "sc": "\u00a7 31-2991(b)(B)", "x": "Ensure dissemination of best practices among Obstetrician/Gynecologist prac"}, {"t": "(C)", "p": "/dc/council/code/sections/31-2991.html#(b)(C)", "et": "para", "sc": "\u00a7 31-2991(b)(C)", "x": "Include provisions to study recommendations based on closed Obstetrician/Gy"}], "x": "The legislation shall include a plan which shall:"}]}]}