{"t": "ch. 192. An Act Making appropriations to provide for the expenses of the government of the District of Columbia for the fiscal year ending June thirtieth, nineteen hundred and twelve, and for other purposes.", "p": "/us/congress/laws/public/61-3-ch192.html", "et": "document", "sc": "Stat. 61-3-ch192", "c": [{"t": "\u00a7 7.", "p": "/us/congress/laws/public/61-3-ch192.html#\u00a77", "et": "section", "sc": "\u00a7 7"}, {"t": "\u00a7 8.", "p": "/us/congress/laws/public/61-3-ch192.html#\u00a78", "et": "section", "sc": "\u00a7 8"}]}