{"t": "Chapter 1B. Reducing Single Occupancy Vehicle Use by Encouraging Transit Benefits.", "p": "/dc/council/code/titles/32/chapters/1B/", "et": "container", "dj": "/dc/council/code/index.json", "sc": "Chapter 1B of Title 32", "c": [{"t": "\u00a7 32\u2013151. Definitions.", "p": "/dc/council/code/sections/32-151.html", "et": "section", "sc": "\u00a7 32-151", "c": [{"t": "(1)", "p": "/dc/council/code/sections/32-151.html#(1)", "et": "para", "sc": "\u00a7 32-151(1)", "x": "\"Covered employer\" means an employer with 20 or more employees; provided, t"}, {"t": "(2)", "p": "/dc/council/code/sections/32-151.html#(2)", "et": "para", "sc": "\u00a7 32-151(2)", "x": "\"Employee\" shall have the same meaning as provided in \u00a7 32-1002(2)."}, {"t": "(3)", "p": "/dc/council/code/sections/32-151.html#(3)", "et": "para", "sc": "\u00a7 32-151(3)", "x": "\"Employer\" shall have the same meaning as provided in \u00a7 32-1002(3)."}, {"t": "(4)", "p": "/dc/council/code/sections/32-151.html#(4)", "et": "para", "sc": "\u00a7 32-151(4)", "x": "\"Transit pass\" shall have the same meaning as provided in section 132(f)(5)"}, {"t": "(5)", "p": "/dc/council/code/sections/32-151.html#(5)", "et": "para", "sc": "\u00a7 32-151(5)", "x": "\"Vanpool\" means a \"commuter highway vehicle\" within the meaning of section "}]}, {"t": "\u00a7 32\u2013152. Transportation benefit program.", "p": "/dc/council/code/sections/32-152.html", "et": "section", "sc": "\u00a7 32-152", "c": [{"t": "(a)", "p": "/dc/council/code/sections/32-152.html#(a)", "et": "para", "sc": "\u00a7 32-152(a)", "c": [{"t": "(1)", "p": "/dc/council/code/sections/32-152.html#(a)(1)", "et": "para", "sc": "\u00a7 32-152(a)(1)", "x": "A pre-tax election transportation fringe benefits program that provides com"}, {"t": "(2)", "p": "/dc/council/code/sections/32-152.html#(a)(2)", "et": "para", "sc": "\u00a7 32-152(a)(2)", "x": "An employer-paid benefit program whereby the employer supplies, at the elec"}, {"t": "(3)", "p": "/dc/council/code/sections/32-152.html#(a)(3)", "et": "para", "sc": "\u00a7 32-152(a)(3)", "x": "Employer-provided transportation at no cost to the covered employee in a va"}], "x": "By January 1, 2016, a covered employer shall provide at least one of the fo"}, {"t": "(b)", "p": "/dc/council/code/sections/32-152.html#(b)", "et": "para", "sc": "\u00a7 32-152(b)", "x": "A covered employer who fails to offer at least one transportation benefit p"}]}, {"t": "\u00a7 32\u2013153. Rules.", "p": "/dc/council/code/sections/32-153.html", "et": "section", "sc": "\u00a7 32-153"}]}