{"t": "Chapter 8. Public School Food Services.", "p": "/dc/council/code/titles/38/chapters/8/", "et": "container", "dj": "/dc/council/code/index.json", "sc": "Chapter 8 of Title 38", "c": [{"t": "\u00a7 38\u2013801. Department of Food Services. [Repealed]", "p": "/dc/council/code/sections/38-801.html", "et": "section", "sc": "\u00a7 38-801"}, {"t": "\u00a7 38\u2013802. Powers of Board. [Repealed]", "p": "/dc/council/code/sections/38-802.html", "et": "section", "sc": "\u00a7 38-802"}, {"t": "\u00a7 38\u2013803. Service credit for retirement; deposits. [Repealed]", "p": "/dc/council/code/sections/38-803.html", "et": "section", "sc": "\u00a7 38-803"}, {"t": "\u00a7 38\u2013804. Deposit of revenues and receipts. [Repealed]", "p": "/dc/council/code/sections/38-804.html", "et": "section", "sc": "\u00a7 38-804"}, {"t": "\u00a7 38\u2013805. Equipment appropriations. [Repealed]", "p": "/dc/council/code/sections/38-805.html", "et": "section", "sc": "\u00a7 38-805"}, {"t": "\u00a7 38\u2013806. National School Lunch Act. [Repealed]", "p": "/dc/council/code/sections/38-806.html", "et": "section", "sc": "\u00a7 38-806"}, {"t": "\u00a7 38\u2013807. Audits of accounts. [Repealed]", "p": "/dc/council/code/sections/38-807.html", "et": "section", "sc": "\u00a7 38-807"}, {"t": "\u00a7 38\u2013808. Distribution of commodities. [Repealed]", "p": "/dc/council/code/sections/38-808.html", "et": "section", "sc": "\u00a7 38-808"}, {"t": "\u00a7 38\u2013809. Appropriations for distribution of commodities. [Repealed]", "p": "/dc/council/code/sections/38-809.html", "et": "section", "sc": "\u00a7 38-809"}]}